google/cloud/talent/__init__.py
google/cloud/talent/gapic_version.py
google/cloud/talent/py.typed
google/cloud/talent_v4/__init__.py
google/cloud/talent_v4/gapic_metadata.json
google/cloud/talent_v4/gapic_version.py
google/cloud/talent_v4/py.typed
google/cloud/talent_v4/services/__init__.py
google/cloud/talent_v4/services/company_service/__init__.py
google/cloud/talent_v4/services/company_service/async_client.py
google/cloud/talent_v4/services/company_service/client.py
google/cloud/talent_v4/services/company_service/pagers.py
google/cloud/talent_v4/services/company_service/transports/__init__.py
google/cloud/talent_v4/services/company_service/transports/base.py
google/cloud/talent_v4/services/company_service/transports/grpc.py
google/cloud/talent_v4/services/company_service/transports/grpc_asyncio.py
google/cloud/talent_v4/services/company_service/transports/rest.py
google/cloud/talent_v4/services/company_service/transports/rest_base.py
google/cloud/talent_v4/services/completion/__init__.py
google/cloud/talent_v4/services/completion/async_client.py
google/cloud/talent_v4/services/completion/client.py
google/cloud/talent_v4/services/completion/transports/__init__.py
google/cloud/talent_v4/services/completion/transports/base.py
google/cloud/talent_v4/services/completion/transports/grpc.py
google/cloud/talent_v4/services/completion/transports/grpc_asyncio.py
google/cloud/talent_v4/services/completion/transports/rest.py
google/cloud/talent_v4/services/completion/transports/rest_base.py
google/cloud/talent_v4/services/event_service/__init__.py
google/cloud/talent_v4/services/event_service/async_client.py
google/cloud/talent_v4/services/event_service/client.py
google/cloud/talent_v4/services/event_service/transports/__init__.py
google/cloud/talent_v4/services/event_service/transports/base.py
google/cloud/talent_v4/services/event_service/transports/grpc.py
google/cloud/talent_v4/services/event_service/transports/grpc_asyncio.py
google_cloud_talent-2.18.0.dist-info/licenses/LICENSE
google_cloud_talent-2.18.0.dist-info/METADATA
google_cloud_talent-2.18.0.dist-info/WHEEL
google_cloud_talent-2.18.0.dist-info/top_level.txt
google_cloud_talent-2.18.0.dist-info/RECORD
